AUTHORS.rst
CONTRIBUTING.rst
HISTORY.rst
LICENSE
MANIFEST.in
README.rst
setup.cfg
setup.py
docs/Makefile
docs/authors.rst
docs/conf.py
docs/contributing.rst
docs/history.rst
docs/index.rst
docs/installation.rst
docs/make.bat
docs/readme.rst
docs/usage.rst
numerical_z/__init__.py
numerical_z/ecdi.py
numerical_z/evdfs.py
numerical_z/iaw.py
numerical_z/langmuir.py
numerical_z/numerical_z.py
numerical_z/plasma.py
numerical_z.egg-info/PKG-INFO
numerical_z.egg-info/SOURCES.txt
numerical_z.egg-info/dependency_links.txt
numerical_z.egg-info/not-zip-safe
numerical_z.egg-info/requires.txt
numerical_z.egg-info/top_level.txt
tests/__init__.py
tests/test__numerical_z.py